{"categoriases":
[
{"code":"Appliances","texto":"Accesorios"},
{"code":"MobileApps","texto":"Aplicaciones Móviles"},
{"code":"ArtsAndCrafts","texto":"Arte y Manualidades"},
{"code":"Automotive","texto":"Auto"},
{"code":"Baby","texto":"Bebé"},
{"code":"Beauty","texto":"Belleza"},
{"code":"Books","texto":"Libros"},
{"code":"Music","texto":"Música"},
{"code":"Wireless","texto":"Móviles y Accesorios"},
{"code":"Fashion","texto":"Ropa, Calzado y Joyería"},
{"code":"Collectibles","texto":"Coleccionables"},
{"code":"PCHardware","texto":"Computadoras"},
{"code":"Electronics","texto":"Electrónica"},
{"code":"HealthPersonal-Care","texto":"Salud y Cuidado Personal"},
{"code":"HomeGarden","texto":"Hogar y Jardín"},
{"code":"Industrial","texto":"Industria y Ciencia"},
{"code":"Luggage","texto":"Equipaje"},
{"code":"Movies","texto":"Películas"},
{"code":"MusicalInstruments","texto":"Instrumentos Musicales"},
{"code":"OfficeProducts","texto":"Productos de Oficina"},
{"code":"PetSupplies","texto":"Mascotas"},
{"code":"Software","texto":"Software"},
{"code":"SportingGoods","texto":"Artículos Deportivos"},
{"code":"Tools","texto":"Herramientas"},
{"code":"Toys","texto":"Juguetes y Juegos"},
{"code":"VideoGames","texto":"Videojuegos"}
]}